<Timestamps>
	<Entry Path="texture\Shingles_Asphalt_001_NORM.jpg" Timestamp="13312662991"/>
	<Entry Path="enbg_edgelight\enbg_edgelight.xml" Timestamp="13312663089"/>
	<Entry Path="texture\CorrugatedMetalPanel02_1K_Normal.png" Timestamp="13312662678"/>
	<Entry Path="texture\blue_painted_planks_disp_4k_comp.png" Timestamp="13312662678"/>
	<Entry Path="enbg_hangar\enbg_hangar.bin" Timestamp="13312675323"/>
	<Entry Path="enbg_house\enbg_house.xml" Timestamp="13312678135"/>
	<Entry Path="texture\Metal024_1K_NormalGL.png" Timestamp="13312662991"/>
	<Entry Path="enbg_edgebeam\enbg_edgebeam.gltf" Timestamp="13312711433"/>
	<Entry Path="texture\Concrete032_2K_Color.png" Timestamp="13312662991"/>
	<Entry Path="texture\Plastic006_1K_Comp.png" Timestamp="13312662991"/>
	<Entry Path="texture\MetalWalkway011_1K_NormalGL.png" Timestamp="13312662991"/>
	<Entry Path="enbg_house\enbg_house.gltf" Timestamp="13312678156"/>
	<Entry Path="enbg_edgebeam\enbg_edgebeam.bin" Timestamp="13312711433"/>
	<Entry Path="enbg_edgelight\enbg_edgelight.gltf" Timestamp="13312663089"/>
	<Entry Path="texture\Metal010_1K_NormalGL.jpg" Timestamp="13312663110"/>
	<Entry Path="enbg_hangar\enbg_hangar.gltf" Timestamp="13312675323"/>
	<Entry Path="texture\Plastic006_1K_NormalGL.png" Timestamp="13312662991"/>
	<Entry Path="texture\Concrete032_2K_Comp.png" Timestamp="13312662991"/>
	<Entry Path="texture\GravelWall01_4K_Normal.png" Timestamp="13312662991"/>
	<Entry Path="texture\CorrugatedMetalPanel02_1K_COMP.png" Timestamp="13312662678"/>
	<Entry Path="texture\Shingles_Asphalt_001_COLOR.png" Timestamp="13312662991"/>
	<Entry Path="texture\Plastic010_1K_COMP.png" Timestamp="13312663110"/>
	<Entry Path="texture\Metal010_1K_Color.png" Timestamp="13312663110"/>
	<Entry Path="texture\Plastic007_1K_NormalGL.png" Timestamp="13312662991"/>
	<Entry Path="texture\extinguisher_sign3.png" Timestamp="13312662991"/>
	<Entry Path="texture\brown_planks_05_diff_1k.png" Timestamp="13312663110"/>
	<Entry Path="texture\blue_painted_planks_diff_4k.png" Timestamp="13312662678"/>
	<Entry Path="texture\blue_painted_planks_rough_4k.jpg" Timestamp="13312662678"/>
	<Entry Path="texture\brown_planks_05_nor_gl_1k.png" Timestamp="13312663110"/>
	<Entry Path="texture\CorrugatedMetalPanel02_1K_BaseColor.png" Timestamp="13312662678"/>
	<Entry Path="texture\blue_painted_planks_nor_gl_2k.png" Timestamp="13312662678"/>
	<Entry Path="texture\dark_planks_nor_gl_1k.png" Timestamp="13312662678"/>
	<Entry Path="texture\Plastic006_1K_Color.png" Timestamp="13312662991"/>
	<Entry Path="texture\MetalWalkway011_1K_Color.png" Timestamp="13312662991"/>
	<Entry Path="texture\GravelWall01_4K_Comp.png" Timestamp="13312674760"/>
	<Entry Path="texture\garage_door.png" Timestamp="13312662991"/>
	<Entry Path="texture\extinguisher_sign4.png" Timestamp="13312662991"/>
	<Entry Path="texture\enbg_main_sign.png" Timestamp="13312662991"/>
	<Entry Path="texture\dark_planks_diff_1k.png" Timestamp="13312662678"/>
	<Entry Path="texture\Metal010_1K_Comp.jpg" Timestamp="13312663110"/>
	<Entry Path="texture\Metal024_1K_Color.png" Timestamp="13312662991"/>
	<Entry Path="texture\blue_painted_planks_nor_gl_4k.png" Timestamp="13312662678"/>
	<Entry Path="texture\Metal024_1K_COMP.png" Timestamp="13312662991"/>
	<Entry Path="texture\doorv2.png" Timestamp="13312662991"/>
	<Entry Path="texture\sign_door.png" Timestamp="13312662991"/>
	<Entry Path="texture\1K-garage_door-ao.png" Timestamp="13312662678"/>
	<Entry Path="enbg_house\enbg_house.bin" Timestamp="13312678156"/>
	<Entry Path="enbg_hangar\enbg_hangar.xml" Timestamp="13312675322"/>
	<Entry Path="texture\Plastic010_1K_NormalGL.png" Timestamp="13312663110"/>
	<Entry Path="texture\brown_planks_05_diff_1k_comp.jpg" Timestamp="13312663110"/>
	<Entry Path="texture\Concrete032_2K_NormalGL.png" Timestamp="13312662991"/>
	<Entry Path="enbg_edgelight\enbg_edgelight.bin" Timestamp="13312663089"/>
	<Entry Path="texture\GravelWall01_4K_BaseColor.png" Timestamp="13312662991"/>
	<Entry Path="texture\super_rough_1k_comp.png" Timestamp="13312662678"/>
	<Entry Path="enbg_edgebeam\enbg_edgebeam.xml" Timestamp="13312711432"/>
	<Entry Path="texture\Plastic010_1K_Color.png" Timestamp="13312663110"/>
	<Entry Path="texture\Plastic007_1K_Color.png" Timestamp="13312662991"/>
	<Entry Path="texture\1K-garage_door-normal.jpg" Timestamp="13312662678"/>
	<Entry Path="texture\dark_planks_comp_1k.jpg" Timestamp="13312662678"/>
	<Entry Path="texture\MetalWalkway011_1K_Comp.png" Timestamp="13312662991"/>
	<Entry Path="texture\extinguisher_sign2.png" Timestamp="13312662991"/>
</Timestamps>

